facebook/__init__.py
facebook/version.py
facebook_sdk-3.0.0.dist-info/METADATA
facebook_sdk-3.0.0.dist-info/RECORD
facebook_sdk-3.0.0.dist-info/WHEEL
facebook_sdk-3.0.0.dist-info/top_level.txt
