Metadata-Version: 1.2
Name: facebook-sdk
Version: 3.0.0
Summary: This client library is designed to support the Facebook Graph API and the official Facebook JavaScript SDK, which is the canonical way to implement Facebook authentication.
Home-page: https://github.com/mobolic/facebook-sdk
Author: Facebook
Maintainer: Martey Dodoo
Maintainer-email: martey+facebook-sdk@mobolic.com
License: Apache
Platform: UNKNOWN
Classifier: License :: OSI Approved :: Apache Software License
Classifier: Programming Language :: Python
Classifier: Programming Language :: Python :: 2.7
Classifier: Programming Language :: Python :: 3
Classifier: Programming Language :: Python :: 3.4
Classifier: Programming Language :: Python :: 3.5
Classifier: Programming Language :: Python :: 3.6
Classifier: Programming Language :: Python :: 3.7
